pymeshtool/__init__.py
pymeshtool/_cext.cpython-313-x86_64-linux-gnu.so
pymeshtool/_cext.pyi
pymeshtool.libs/libgomp-e985bcbb.so.1.0.0
pymeshtool-1.1.0.dist-info/METADATA
pymeshtool-1.1.0.dist-info/WHEEL
pymeshtool-1.1.0.dist-info/top_level.txt
pymeshtool-1.1.0.dist-info/RECORD
pymeshtool-1.1.0.dist-info/licenses/LICENSE
pymeshtool-1.1.0.dist-info/sboms/auditwheel.cdx.json
