Metadata-Version: 2.4
Name: pymeshtool
Version: 1.1.0
Summary: Python3 bindings for MeshTool.
Author: Matthias A.F. Gsell
Author-email: "Matthias A.F. Gsell" <pymeshtool@medunigraz.at>, "Benedikt A. Klöckl" <benedikt.kloeckl@medunigraz.at>
Maintainer-email: "Matthias A.F. Gsell" <pymeshtool@medunigraz.at>
License-Expression: GPL-3.0-only
Project-URL: Homepage, https://carpentry.medunigraz.at/pymeshtool
Project-URL: MeshTool, https://bitbucket.org/aneic/meshtool
Project-URL: Computational Cardiology Lab, https://ccl.medunigraz.at
Keywords: meshtool,model generation,mesh manipulation
Classifier: Programming Language :: Python :: 3.9
Classifier: Programming Language :: Python :: 3.10
Classifier: Programming Language :: Python :: 3.11
Classifier: Programming Language :: Python :: 3.12
Classifier: Programming Language :: Python :: 3.13
Classifier: Programming Language :: C++
Classifier: Programming Language :: C
Classifier: Operating System :: MacOS
Classifier: Operating System :: POSIX :: Linux
Classifier: Topic :: Software Development :: Testing
Requires-Python: >=3.9
License-File: LICENSE
Requires-Dist: numpy>=1.19; python_version >= "3.9" and python_version < "3.10"
Requires-Dist: numpy>=1.21; python_version >= "3.10" and python_version < "3.11"
Requires-Dist: numpy>=1.23; python_version >= "3.11" and python_version < "3.12"
Requires-Dist: numpy>=1.25; python_version >= "3.12"
Dynamic: author
Dynamic: license-file
Dynamic: requires-python
